{
  "case_id": "book5_r1\\046.json",
  "input": {
    "background": "Data from 37 patients receiving a non-depleted allogeneic bone marrow transplant were examined to see which variables were associated with the development of acute graft-versus-host disease (GvHD). The data includes recipient and donor ages, type of leukemia, donor pregnancy status, and an index of mixed epidermal cell-lymphocyte reactions. Donor pregnancy is coded 0 for No and 1 for Yes. Type of leukemia is coded 1 (acute myeloid leukemia - AML), 2 (acute lymphocytic leukemia - ALL), or 3 (chronic myeloid leukemia - CML). Survival time is also provided but is not used in the analysis.",
    "data": "\\documentclass{article}\n\\usepackage{booktabs,multirow}\n\\begin{document}\n\\begin{table}[htbp]\n  \\centering\n  \\begin{tabular}{lcccccc}\n    Patient & Recipient age & Donor age & Type & Preg & Index & Survival time (days) \\\\\n    \\midrule\n    \\multicolumn{7}{l}{Patients without GvHD} \\\\\n    1  & 27 & 23 & 2 & 0 & 0.27 & 95 \\\\\n    2  & 13 & 18 & 2 & 0 & 0.31 & 1385* \\\\\n    3  & 19 & 19 & 1 & 0 & 0.39 & 465 \\\\\n    4  & 21 & 22 & 2 & 0 & 0.48 & 810 \\\\\n    5  & 28 & 38 & 2 & 0 & 0.49 & 1497* \\\\\n    6  & 22 & 20 & 2 & 0 & 0.50 & 1181 \\\\\n    7  & 19 & 19 & 2 & 0 & 0.81 & 993* \\\\\n    8  & 20 & 23 & 2 & 0 & 0.82 & 138 \\\\\n    9  & 33 & 36 & 1 & 0 & 0.86 & 266 \\\\\n    10 & 18 & 19 & 1 & 0 & 0.92 & 579* \\\\\n    11 & 17 & 20 & 2 & 0 & 1.10 & 600* \\\\\n    12 & 31 & 21 & 3 & 0 & 1.52 & 1182* \\\\\n    13 & 23 & 38 & 2 & 0 & 1.88 & 841* \\\\\n    14 & 17 & 15 & 2 & 0 & 2.01 & 1364* \\\\\n    15 & 26 & 16 & 2 & 0 & 2.40 & 695* \\\\\n    16 & 28 & 25 & 1 & 0 & 2.45 & 1378* \\\\\n    17 & 24 & 21 & 1 & 1 & 2.60 & 736* \\\\\n    18 & 18 & 20 & 2 & 0 & 2.64 & 1504* \\\\\n    19 & 24 & 25 & 1 & 1 & 3.78 & 849 \\\\\n    20 & 20 & 24 & 3 & 0 & 4.72 & 1266* \\\\\n    \\midrule\n    \\multicolumn{7}{l}{Patients with GvHD} \\\\\n    21 & 23 & 35 & 1 & 1 & 1.10 & 186 \\\\\n    22 & 21 & 35 & 2 & 1 & 1.16 & 41 \\\\\n    23 & 21 & 23 & 3 & 0 & 1.45 & 667* \\\\\n    24 & 33 & 43 & 3 & 0 & 1.50 & 112 \\\\\n    25 & 29 & 24 & 3 & 1 & 1.85 & 572* \\\\\n    26 & 42 & 35 & 2 & 1 & 2.30 & 45 \\\\\n    27 & 27 & 31 & 3 & 0 & 2.34 & 1019* \\\\\n    28 & 43 & 29 & 2 & 1 & 2.44 & 479 \\\\\n    29 & 22 & 20 & 1 & 0 & 3.70 & 190 \\\\\n    30 & 35 & 39 & 1 & 1 & 3.73 & 100 \\\\\n    31 & 16 & 14 & 1 & 0 & 4.13 & 177 \\\\\n  \\end{tabular}\n\\end{table}\n\n\\begin{table}[htbp]\n  \\centering\n  \\caption{Exercises 363}\n  \\vspace{5pt}\n  \\begin{tabular}{lcccccc}\n    Patient & Recipient age & Donor age & Type & Preg & Index & Survival time (days) \\\\\n    32 & 39 & 35 & 2 & 1 & 4.52 & 80 \\\\\n    33 & 28 & 25 & 3 & 1 & 4.52 & 142 \\\\\n    34 & 29 & 32 & 3 & 0 & 4.71 & 1105* \\\\\n    35 & 23 & 19 & 3 & 0 & 5.07 & 803* \\\\\n    36 & 33 & 34 & 3 & 0 & 9.00 & 1126* \\\\\n    37 & 19 & 20 & 1 & 0 & 10.11 & 114 \\\\\n  \n  \\end{tabular}\n\\end{table}\n\n\\end{document}",
    "question": "Calculate the odds ratio for the risk of GvHD in relation to each binary variable in the model, with a 90% confidence interval."
  },
  "output": {
    "answer": "For a binary variable in a logistic regression model, the odds ratio (OR) is given by e^b, where b is the estimated regression coefficient. The 90% confidence interval (CI) is obtained as e^(b ± 1.645 × SE(b)).\n\nFor CML:\nOR = e^2.251 = 9.5\n90% CI = [e^(2.251 - 1.645 × 1.106), e^(2.251 + 1.645 × 1.106)] = [1.54, 58.6]\n\nFor pregnancy:\nOR = e^2.496 = 12.1\n90% CI = [e^(2.496 - 1.645 × 1.101), e^(2.496 + 1.645 × 1.101)] = [1.98, 74.2]\n\nBoth confidence intervals are extremely wide, indicating that precise estimates cannot be obtained from a sample this small."
  },
  "meta_info": {
    "index": "12.3",
    "img_in_question": null,
    "img_in_answer": null,
    "caption": null,
    "chapter": "Relation between several variables",
    "section": "EXERCISES",
    "book": "Practical statistics for medical research",
    "page": "361-363"
  },
  "sample_key": "131"
}