{
  "case_id": "book5_r1\\044.json",
  "input": {
    "background": "The table below shows data from an experiment to compare resting metabolic rates (kcal/min) in five volunteers each given two diets, a normal diet and an overfeeding diet which contained 50% more energy (Welle et al., 1986). Data were collected before and after eating a meal.",
    "data": "\\begin{tabular}{|l|l|l|l|}\n\\hline Subject & Diet & Before meal & After meal \\\\\n\\hline 1 & N & 1.47 & 1.78 \\\\\n\\hline & O & 1.72 & 2.49 \\\\\n\\hline 2 & N & 1.42 & 1.68 \\\\\n\\hline & O & 1.44 & 1.87 \\\\\n\\hline 3 & N & 1.10 & 1.26 \\\\\n\\hline & O & 1.11 & 1.36 \\\\\n\\hline 4 & N & 0.84 & 1.11 \\\\\n\\hline & O & 0.90 & 1.29 \\\\\n\\hline 5 & N & 0.91 & 1.09 \\\\\n\\hline & O & 1.00 & 1.25 \\\\\n\\hline\n\\end{tabular}\n\nN : Normal diet: O : Overfed diet",
    "question": "What methods of analysis could be used to examine the difference between the metabolic rates in relation to diet: (i) for the post-prandial data; (ii) for the change between pre- and post-prandial resting metabolic rates?"
  },
  "output": {
    "method": "均值检验",
    "answer": "(i) A paired t test or, equivalently, a two way analysis of variance. (ii) Same as (i)."
  },
  "meta_info": {
    "index": "12.1",
    "img_in_question": null,
    "img_in_answer": null,
    "caption": null,
    "chapter": "Relation between several variables",
    "section": "EXERCISES",
    "book": "Practical statistics for medical research",
    "page": "361-361"
  },
  "sample_key": "99"
}