{
  "case_id": "book1_r1\\record_081.json",
  "input": {
    "background": "A jury having heard the evidence in a criminal case, is debating whether to render a verdict of guilty or not guilty. Because it is worse to convict an innocent person of a crime they did not commit than let a guilty person go free, each case starts with a presumption of innocence. This is analogous to the presumption that H0 is true in a statistical hypothesis test. Other analogies exist.",
    "data": "",
    "question": "Which type of decision is analogous to a type I error?"
  },
  "output": {
    "answer": "Declaring an innocent person guilty (b) is analogous to a type I error."
  },
  "meta_info": {
    "index": "9.19",
    "image": "",
    "caption": "The criminal justice analogy.",
    "chapter": "BASICS OF HYPOTHESIS TESTING",
    "section": "9.6 POWER AND SAMPLE SIZE",
    "page": "195-195"
  },
  "sample_key": "186"
}