{
  "case_id": "book1_r1\\record_318.json",
  "input": {
    "background": "Consider this small ordered array (n=10): 5, 11, 21, 24, 27, 28, 30, 42, 50, 52. The positions of Q1, M, and Q3 are marked in the array.",
    "data": "",
    "question": "What is the high group and the value of Q3?"
  },
  "output": {
    "answer": "The high group is {28, 30, 42, 50, 52}, so Q3 = 42."
  },
  "meta_info": {
    "index": "",
    "image": "",
    "caption": "Quartiles.",
    "chapter": "SUMMARY STATISTICS",
    "section": "4.5 SPREAD: QUARTILES",
    "page": "73-73"
  },
  "sample_key": "453"
}