{
  "case_id": "book1_r1\\record_392.json",
  "input": {
    "background": "We calculate the 95% confidence interval for μ1−μ2 for the cholesterol illustrative data (see Table 12.5).",
    "data": "Table 12.5 ",
    "question": "What is the 95% confidence interval for μ1−μ2 using the conservative method?"
  },
  "output": {
    "answer": "The 95% confidence interval is (x̄1−x̄2) ± t(df, 1−α/2)(SE(x̄1−x̄2)) = 0.777 ± (2.447)(0.2702) = 0.777 ± 0.661 = 0.116 to 1.438 (mmol/L)."
  },
  "meta_info": {
    "index": "",
    "image": "",
    "caption": "Confidence interval for $\\\\mu_1-\\\\mu_2$.",
    "chapter": "COMPARING INDEPENDENT MEANS",
    "section": "12.3 INFERENCE ABOUT THE MEAN DIFFERENCE",
    "page": "244-245"
  },
  "sample_key": "615"
}